niiv/__init__.py
niiv/feature_grid.py
niiv/models.py
niiv/regularizer.py
niiv/decoder/__init__.py
niiv/decoder/field_siren.py
niiv/decoder/inr.py
niiv/decoder/mlp.py
niiv/decoder/pos_enc.py
niiv/decoder/sine_layer.py
niiv/decoder/wire.py
niiv/encoders/__init__.py
niiv/encoders/edsr_2d.py
niiv/encoders/rdn.py
niiv/encoders/swinir.py
niiv/util/__init__.py
niiv/util/clahe.py
niiv/util/eval_metrics.py
niiv/util/loss_functions.py
niiv/util/transforms.py
niiv/util/utils.py
util/__init__.py
util/clahe.py
util/eval_metrics.py
util/loss_functions.py
util/transforms.py
util/utils.py
niiv-0.0.5.dist-info/LICENSE
niiv-0.0.5.dist-info/METADATA
niiv-0.0.5.dist-info/WHEEL
niiv-0.0.5.dist-info/top_level.txt
niiv-0.0.5.dist-info/RECORD
