Metadata-Version: 2.1
Name: niiv
Version: 0.0.5
Summary: Self-Supervised Neural Implicit Isotropic Volume Reconstruction
Home-page: https://niiv.net
Author: Anonymous Anonymous
Author-email: anonymous@anonymous.com
Classifier: Programming Language :: Python :: 3
Classifier: License :: OSI Approved :: MIT License
Classifier: Operating System :: OS Independent
License-File: LICENSE
Requires-Dist: torch
Requires-Dist: DISTS-pytorch
Requires-Dist: lpips
Requires-Dist: numpy
Requires-Dist: pytorch-ignite
Requires-Dist: tqdm
Requires-Dist: wandb
Requires-Dist: pytorch-msssim
